MANIFEST.in
README.rst
setup.py
vsource_algorithm/__init__.py
vsource_algorithm/configs.py
vsource_algorithm/loginInstance.py
vsource_algorithm.egg-info/PKG-INFO
vsource_algorithm.egg-info/SOURCES.txt
vsource_algorithm.egg-info/dependency_links.txt
vsource_algorithm.egg-info/requires.txt
vsource_algorithm.egg-info/top_level.txt
vsource_algorithm/algorithms/__init__.py
vsource_algorithm/algorithms/face_attribute.py
vsource_algorithm/algorithms/face_detection.py
vsource_algorithm/algorithms/face_recognition.py
vsource_algorithm/algorithms/speaker_recognition.py
vsource_algorithm/exceptions/__init__.py
vsource_algorithm/scripts/__init__.py
vsource_algorithm/scripts/algorithm_scripts/__init__.py
vsource_algorithm/scripts/algorithm_scripts/algorithm-configs.template
vsource_algorithm/scripts/algorithm_scripts/algorithm-deploy-compose.template
vsource_algorithm/scripts/algorithm_scripts/algorithm-deploy-kube.template
vsource_algorithm/scripts/algorithm_scripts/algorithm-dockerfile.template
vsource_algorithm/scripts/algorithm_scripts/algorithm-service.template
vsource_algorithm/scripts/algorithm_scripts/algorithms.py