Metadata-Version: 1.2
Name: vsource-algorithm
Version: 1.0.12
Summary: Algorithm python library linked to vsource platform.
Home-page: https://github.com/VSOURCE-Platform/VSOURCE-Library
Author: Ecohnoch
Author-email: 542305306@qq.com
Maintainer: Ecohnoch
Maintainer-email: 542305306@qq.com
License: BSD License
Platform: all
Classifier: Development Status :: 4 - Beta
Classifier: Operating System :: OS Independent
Classifier: Intended Audience :: Developers
Classifier: License :: OSI Approved :: BSD License
Classifier: Programming Language :: Python :: 3.6
Classifier: Topic :: Software Development :: Libraries
